Metadata-Version: 2.1
Name: odoo12-addon-sale_automatic_workflow_job
Version: 12.0.1.0.2
Summary: Execute sale automatic workflows in queue jobs
Home-page: https://github.com/OCA/sale-workflow
Author: Camptocamp, Odoo Community Association (OCA)
Author-email: support@odoo-community.org
License: AGPL-3
Classifier: Programming Language :: Python
Classifier: Framework :: Odoo
Classifier: Framework :: Odoo :: 12.0
Classifier: License :: OSI Approved :: GNU Affero General Public License v3
Requires-Python: >=3.5
Requires-Dist: odoo12-addon-queue-job
Requires-Dist: odoo12-addon-sale-automatic-workflow
Requires-Dist: odoo<12.1dev,>=12.0a
